hg_delivery/__init__.py
hg_delivery/interfaces.py
hg_delivery/models.py
hg_delivery/nodes.py
hg_delivery/predicates.py
hg_delivery/routes.py
hg_delivery/security.py
hg_delivery/subscribers.py
hg_delivery/tests.py
hg_delivery/tools.py
hg_delivery/views.py
hg_delivery/models/__init__.py
hg_delivery/models/hgd_model.py
hg_delivery/models/meta.py
hg_delivery/scripts/__init__.py
hg_delivery/scripts/initializedb.py
hg_delivery/static/codemirror.css
hg_delivery/static/codemirror.js
hg_delivery/static/codemirror.min.js
hg_delivery/static/d3.v3.min.js
hg_delivery/static/delivery.css
hg_delivery/static/delivery.js
hg_delivery/static/jquery-1.11.1.min.js
hg_delivery/static/mergely.css
hg_delivery/static/mergely.js
hg_delivery/static/mergely.min.js
hg_delivery/static/pyramid-16x16.png
hg_delivery/static/pyramid.png
hg_delivery/static/searchcursor.js
hg_delivery/static/theme.css
hg_delivery/static/theme.min.css
hg_delivery/static/typeahead.bundle.js
hg_delivery/static/bootstrap-3.1.1/css/bootstrap-theme.css
hg_delivery/static/bootstrap-3.1.1/css/bootstrap-theme.min.css
hg_delivery/static/bootstrap-3.1.1/css/bootstrap.css
hg_delivery/static/bootstrap-3.1.1/css/bootstrap.min.css
hg_delivery/static/bootstrap-3.1.1/js/bootstrap.js
hg_delivery/static/bootstrap-3.1.1/js/bootstrap.min.js
hg_delivery/templates/base.mako
hg_delivery/templates/contact.mako
hg_delivery/templates/edit.mako
hg_delivery/templates/index.mako
hg_delivery/templates/lib.mako
hg_delivery/templates/macros.mako
hg_delivery/templates/revision.mako
hg_delivery/templates/tasks.mako
hg_delivery/templates/users.mako
hg_delivery/templates/view_group.mako
hg_delivery/tests/__init__.py
hg_delivery/tests/test_contact.py
hg_delivery/tests/test_logs.py
hg_delivery/tests/test_macro.py
hg_delivery/tests/test_project.py
hg_delivery/tests/test_pushpull.py
hg_delivery/tests/test_tasks.py
hg_delivery/tests/test_user.py
hg_delivery-1.1.7.dist-info/LICENSE.txt
hg_delivery-1.1.7.dist-info/METADATA
hg_delivery-1.1.7.dist-info/WHEEL
hg_delivery-1.1.7.dist-info/entry_points.txt
hg_delivery-1.1.7.dist-info/top_level.txt
hg_delivery-1.1.7.dist-info/RECORD
