Metadata-Version: 2.1
Name: hg-delivery
Version: 1.1.7
Summary: HgDelivery is an easy way to deliver products  for Mercurial and Git with a built in push/pull server, as well as repositories comparison
Home-page: https://bitbucket.org/tuck/hg_delivery
Author: Stéphane Bard
Author-email: stephane.bard@gmail.com
License: UNKNOWN
Keywords: web pyramid hg mercurial git
Platform: UNKNOWN
Classifier: Development Status :: 5 - Production/Stable
Classifier: Environment :: Web Environment
Classifier: Framework :: Pyramid
Classifier: Intended Audience :: Developers
Classifier: License :: OSI Approved :: MIT License
Classifier: Operating System :: OS Independent
Classifier: Programming Language :: Python
Classifier: Programming Language :: Python :: 3.6
Classifier: Programming Language :: Python :: 3.7
Classifier: Programming Language :: Python :: 3.8
Classifier: Topic :: Software Development :: Version Control
Requires-Dist: SQLAlchemy
Requires-Dist: alembic
Requires-Dist: apscheduler (==2.1.2)
Requires-Dist: coverage
Requires-Dist: kombu (==4.6.7)
Requires-Dist: mock
Requires-Dist: mock-alchemy
Requires-Dist: paramiko (==2.7.1)
Requires-Dist: pygments
Requires-Dist: pyramid
Requires-Dist: pyramid-scheduler (==0.3.4)
Requires-Dist: pyramid-mailer
Requires-Dist: pyramid-mako
Requires-Dist: pyramid-tm
Requires-Dist: pytest
Requires-Dist: redis (==3.3.11)
Requires-Dist: transaction
Requires-Dist: vine (==1.3.0)
Requires-Dist: waitress
Requires-Dist: zope.component
Requires-Dist: zope.interface (>=3.8.0)
Requires-Dist: zope.sqlalchemy
